Metadata-Version: 2.1
Name: inkprint
Version: 1.1
Summary: A simple way to print texts with colors.
Home-page: UNKNOWN
Author: Shi Shu
Author-email: shushi20002003@gmail.com
License: UNKNOWN
Platform: UNKNOWN
